Workbook
Name aporte_divers: 'Plano de Investimento'!$F$37
Name aporte_rendafix: 'Plano de Investimento'!$F$18
Name aporte_rendavar: 'Plano de Investimento'!$F$26
Name dividendo_10: 'Plano de Investimento'!$E$31
Name dividendo_1o: 'Plano de Investimento'!$E$31
Name dividendo_2: 'Plano de Investimento'!$E$29
Name dividendo_20: 'Plano de Investimento'!$E$32
Name dividendo_30: 'Plano de Investimento'!$E$33
Name dividendo_5: 'Plano de Investimento'!$E$30
Name DY_rendavar: 'Plano de Investimento'!$E$26
Name periodo_rendafix: 'Plano de Investimento'!$D$18
Name rendimento_10_rendavar: 'Plano de Investimento'!$D$31
Name rendimento_2_rendavar: 'Plano de Investimento'!$D$29
Name rendimento_20_rendavar: 'Plano de Investimento'!$D$32
Name rendimento_30_rendavar: 'Plano de Investimento'!$D$33
Name rendimento_5_rendavar: 'Plano de Investimento'!$D$30
Name rendimento_rendafix: 'Plano de Investimento'!$D$19
Name rendimento_rendavar: 'Plano de Investimento'!$C$26
Name reserva_rendavar: 'Plano de Investimento'!$E$25
Name salario: 'Plano de Investimento'!$C$25
Name valor_mensal_10: 'Plano de Investimento'!$C$31
Name valor_mensal_2: 'Plano de Investimento'!$C$29
Name valor_mensal_20: 'Plano de Investimento'!$C$32
Name valor_mensal_30: 'Plano de Investimento'!$C$33
Name valor_mensal_5: 'Plano de Investimento'!$C$30

Sheet Plano de Investimento
B9: Invest | D9: Simuladores de Investimentos
B10: Rafa | D10: Planejando seu futuro
B16: Simulação de de Investimento contante em Renda Fixa. Ajuste os parâmetros "Período", "Rendimento Mensal" e "Aporte" para visualizar o resultado.
B18: Período (anos): | D18: 10 | E18: Aporte: | F18: 1000
B19: Rendimento Mensal (situação a curto prazo): | D19: 0.01
B20: Investimento Mensal -Renda Fixa
B21: Rendimento Total no fim do período: | D21: =FV(rendimento_rendafix,periodo_rendafix*12,aporte_rendafix*-1) -> 230038.69
B23: Simulação de de Investimento a longo prazo em Renda Variável. Ajuste os parâmetros "Salário", "Reserva para Investimento", "Valorização" e "Dividendo Anual" para visualizar o resultado.
B25: Salário: | C25: 10000 | D25: Reserva para Investimento: | E25: 0.1 | F25: Aporte
B26: Valorização Carteira Variável (média mensal a longo prazo): | C26: 0.015 | D26: Dividendo Anual (DY): | E26: 0.15 | F26: =salario*reserva_rendavar -> 1000
B27: Investimento - Renda Variável
B28: Período | C28: Valorização/Mês | D28: Rendimento | E28: Dividendo Anual (DY) | F28: TOTAL Renda + DY
A29: 24 | B29: Quanto em 2 Anos? | C29: =rendimento_2_rendavar*rendimento_rendavar -> 429.50281 | D29: =FV(rendimento_rendavar,A29,aporte_rendavar)*-1 -> 28633.521 | E29: =rendimento_2_rendavar*DY_rendavar -> 4295.0281 | F29: =SUM(dividendo_2,rendimento_2_rendavar) -> 32928.549
A30: 60 | B30: Quanto em 5 Anos? | C30: =rendimento_5_rendavar*rendimento_rendavar -> 1443.2198 | D30: =FV(rendimento_rendavar,A30,aporte_rendavar)*-1 -> 96214.652 | E30: =rendimento_5_rendavar*DY_rendavar -> 14432.198 | F30: =SUM(dividendo_5,rendimento_5_rendavar) -> 110646.85
A31: 120 | B31: Quanto em 10 Anos? | C31: =rendimento_10_rendavar*rendimento_rendavar -> 4969.3229 | D31: =FV(rendimento_rendavar,A31,aporte_rendavar)*-1 -> 331288.19 | E31: =rendimento_10_rendavar*DY_rendavar -> 49693.229 | F31: =SUM(dividendo_10,rendimento_10_rendavar) -> 380981.42
A32: 240 | B32: Quanto em 20 Anos? | C32: =rendimento_20_rendavar*rendimento_rendavar -> 34632.816 | D32: =FV(rendimento_rendavar,A32,aporte_rendavar)*-1 -> 2308854.4 | E32: =rendimento_20_rendavar*DY_rendavar -> 346328.16 | F32: =SUM(dividendo_20,rendimento_20_rendavar) -> 2655182.5
A33: 360 | B33: Quanto em 30 Anos? | C33: =rendimento_30_rendavar*rendimento_rendavar -> 211703.78 | D33: =FV(rendimento_rendavar,A33,aporte_rendavar)*-1 -> 14113585 | E33: =rendimento_30_rendavar*DY_rendavar -> 2117037.8 | F33: =SUM(dividendo_30,rendimento_30_rendavar) -> 16230623
B35: Configure o seu "Perfil de Investidor" e receba sugestão de Diversificação de sua Carteira
B37: Perfil de Investidor: | C37: Conservador | E37: Aporte por Mês: | F37: =aporte_rendavar -> 1000
B38: Diversificação da Carteira de Investimentos
B39: Nível de Risco | C39: Tipos de Investimentos | E39: Percentual Sugerido | F39: Valores
B40: 1 | C40: Tesouro Selic; CDBs de grandes bancos; LCIs/LCAs; Fundos DI; Poupança | E40: =VLOOKUP($C$37&"-"&C40,'Tabela de Apoio Chaves'!$B$4:$E$18,4,FALSE) -> 0.4 | F40: =$F$37*E40 -> 400
B41: 2 | C41: ETFs amplos e diversificados; FIIs de tijolo; ações de grandes empresas (blue chips) | E41: =VLOOKUP($C$37&"-"&C41,'Tabela de Apoio Chaves'!$B$4:$E$18,4,FALSE) -> 0.3 | F41: =$F$37*E41 -> 300
B42: 3 | C42: Ações de empresas médias; FIIs de papel; ETFs setoriais; fundos de ações ativos | E42: =VLOOKUP($C$37&"-"&C42,'Tabela de Apoio Chaves'!$B$4:$E$18,4,FALSE) -> 0.2 | F42: =$F$37*E42 -> 200
B43: 4 | C43: Small caps; BDRs; commodities; derivativos simples (opções, futuros) | E43: =VLOOKUP($C$37&"-"&C43,'Tabela de Apoio Chaves'!$B$4:$E$18,4,FALSE) -> 0.1 | F43: =$F$37*E43 -> 100
B44: 5 | C44: Criptomoedas; derivativos alavancados; penny stocks | E44: =VLOOKUP($C$37&"-"&C44,'Tabela de Apoio Chaves'!$B$4:$E$18,4,FALSE) -> 0 | F44: =$F$37*E44 -> 0

Sheet Tabela de Apoio Chaves
B3: CHAVE | C3: PERFIL | D3: TIPO DE FII | E3: %
B4: =C4&"-"&D4 -> Conservador-Tesouro Selic; CDBs de grandes bancos; LCIs/LCAs; Fundos DI; Poupança | C4: Conservador | D4: Tesouro Selic; CDBs de grandes bancos; LCIs/LCAs; Fundos DI; Poupança | E4: 0.4
B5: =C5&"-"&D5 -> Conservador-ETFs amplos e diversificados; FIIs de tijolo; ações de grandes empresas (blue chips) | C5: Conservador | D5: ETFs amplos e diversificados; FIIs de tijolo; ações de grandes empresas (blue chips) | E5: 0.3
B6: =C6&"-"&D6 -> Conservador-Ações de empresas médias; FIIs de papel; ETFs setoriais; fundos de ações ativos | C6: Conservador | D6: Ações de empresas médias; FIIs de papel; ETFs setoriais; fundos de ações ativos | E6: 0.2
B7: =C7&"-"&D7 -> Conservador-Small caps; BDRs; commodities; derivativos simples (opções, futuros) | C7: Conservador | D7: Small caps; BDRs; commodities; derivativos simples (opções, futuros) | E7: 0.1
B8: =C8&"-"&D8 -> Conservador-Criptomoedas; derivativos alavancados; penny stocks | C8: Conservador | D8: Criptomoedas; derivativos alavancados; penny stocks | E8: 0
B9: =C9&"-"&D9 -> Moderado-Tesouro Selic; CDBs de grandes bancos; LCIs/LCAs; Fundos DI; Poupança | C9: Moderado | D9: Tesouro Selic; CDBs de grandes bancos; LCIs/LCAs; Fundos DI; Poupança | E9: 0.1
B10: =C10&"-"&D10 -> Moderado-ETFs amplos e diversificados; FIIs de tijolo; ações de grandes empresas (blue chips) | C10: Moderado | D10: ETFs amplos e diversificados; FIIs de tijolo; ações de grandes empresas (blue chips) | E10: 0.3
B11: =C11&"-"&D11 -> Moderado-Ações de empresas médias; FIIs de papel; ETFs setoriais; fundos de ações ativos | C11: Moderado | D11: Ações de empresas médias; FIIs de papel; ETFs setoriais; fundos de ações ativos | E11: 0.3
B12: =C12&"-"&D12 -> Moderado-Small caps; BDRs; commodities; derivativos simples (opções, futuros) | C12: Moderado | D12: Small caps; BDRs; commodities; derivativos simples (opções, futuros) | E12: 0.2
B13: =C13&"-"&D13 -> Moderado-Criptomoedas; derivativos alavancados; penny stocks | C13: Moderado | D13: Criptomoedas; derivativos alavancados; penny stocks | E13: 0.1
B14: =C14&"-"&D14 -> Agressivo-Tesouro Selic; CDBs de grandes bancos; LCIs/LCAs; Fundos DI; Poupança | C14: Agressivo | D14: Tesouro Selic; CDBs de grandes bancos; LCIs/LCAs; Fundos DI; Poupança | E14: 0.05
B15: =C15&"-"&D15 -> Agressivo-ETFs amplos e diversificados; FIIs de tijolo; ações de grandes empresas (blue chips) | C15: Agressivo | D15: ETFs amplos e diversificados; FIIs de tijolo; ações de grandes empresas (blue chips) | E15: 0.05
... B18: =C18&"-"&D18 -> Agressivo-Criptomoedas; derivativos alavancados; penny stocks | C18: Agressivo | D18: Criptomoedas; derivativos alavancados; penny stocks | E18: 0.3
